{
    "LOC": {
        "linesOfCode": 7749,
        "logicalLinesOfCode": 4037,
        "commentLinesOfCode": 3719,
        "avgVolume": 490.23,
        "avgCommentWeight": 43.56,
        "avgIntelligentContent": 43.56,
        "logicalLinesByClass": 46,
        "logicalLinesByMethod": 11
    },
    "OOP": {
        "classes": 88,
        "interface": 29,
        "methods": 356,
        "methodsByClass": 4.05,
        "lackCohesionOfMethods": 2.11
    },
    "Coupling": {
        "avgAfferentCoupling": 0.52,
        "avgEfferentCoupling": 4.72,
        "avgInstability": 0.85,
        "inheritanceTreeDepth": 1.09
    },
    "Package": {
        "packages": 34,
        "acgClassesPerPackage": 3.44,
        "avgDistance": 0.13,
        "avgIncomingClassDependencies": 2.65,
        "avgOutgoingClassDependencies": 5,
        "avgIncomingPackageDependencies": 1.24,
        "avgOutgoingPackageDependencies": 3.82
    },
    "Complexity": {
        "avgCyclomaticComplexityByClass": 8.68,
        "avgWeightedMethodCountByClass": 11.73,
        "avgRelativeSystemComplexity": 183.86,
        "avgDifficulty": 7.57
    },
    "Bugs": {
        "avgBugsByClass": 0.16,
        "avgDefectsByClass": 0.59
    },
    "Violations": {
        "critical": 0,
        "error": 13,
        "warning": 14,
        "information": 0
    }
}